utils/__init__.py
utils/decode.py
utils/encode.py
utils/file.py
utils/lists.py
utils/strings.py
utils/url.py
utils_aazerra-0.1.0.dist-info/LICENSE
utils_aazerra-0.1.0.dist-info/METADATA
utils_aazerra-0.1.0.dist-info/WHEEL
utils_aazerra-0.1.0.dist-info/top_level.txt
utils_aazerra-0.1.0.dist-info/RECORD
