Metadata-Version: 2.1
Name: utils-aazerra
Version: 0.1.0
Summary: a bunch of util functions for personal use
Home-page: https://github.com/Aazerra/utils
Author: Alireza Rabie
Author-email: alirezarabie793@gmail.com
License: MIT
Platform: unix
Platform: linux
Platform: windows
Platform: osx
Classifier: Programming Language :: Python :: 3
Classifier: Programming Language :: Python :: 3 :: Only
Classifier: Programming Language :: Python :: 3.6
Classifier: Programming Language :: Python :: 3.7
Classifier: Programming Language :: Python :: 3.8
Classifier: Programming Language :: Python :: 3.9
Classifier: License :: OSI Approved :: MIT License
Classifier: Operating System :: OS Independent
Requires-Python: >=3.6
License-File: LICENSE
